LICENSE
MANIFEST.in
README.rst
requirements.txt
setup.py
wb_vandalism/__init__.py
wb_vandalism.egg-info/PKG-INFO
wb_vandalism.egg-info/SOURCES.txt
wb_vandalism.egg-info/dependency_links.txt
wb_vandalism.egg-info/requires.txt
wb_vandalism.egg-info/top_level.txt
wb_vandalism/datasources/__init__.py
wb_vandalism/datasources/diff.py
wb_vandalism/datasources/parent_revision.py
wb_vandalism/datasources/revision.py
wb_vandalism/datasources/util.py
wb_vandalism/feature_lists/__init__.py
wb_vandalism/feature_lists/wikidata.py
wb_vandalism/features/__init__.py
wb_vandalism/features/diff.py
wb_vandalism/features/revision.py
wb_vandalism/features/tests/__init__.py
wb_vandalism/features/tests/test_diff.py
wb_vandalism/features/tests/test_revision.py