Metadata-Version: 1.1
Name: wb-vandalism
Version: 0.1.8
Summary: A library for performing automatic detection of vandalism in Wikidata.
Home-page: https://github.com/Ladsgroup/wb-vandalism
Author: Amir Sarabadani
Author-email: Ladsgroup@gmail.com
License: MIT
Platform: UNKNOWN
Classifier: Development Status :: 3 - Alpha
Classifier: Topic :: Software Development :: Libraries :: Python Modules
Classifier: Programming Language :: Python
Classifier: Programming Language :: Python :: 3
Classifier: Intended Audience :: Developers
Classifier: License :: OSI Approved :: MIT License
Classifier: Operating System :: OS Independent
Classifier: Topic :: Utilities
Classifier: Topic :: Scientific/Engineering
